pickaa/__init__.py
pickaa/test_randpicker.py
pickaa-1.0.0.dist-info/LICENSE
pickaa-1.0.0.dist-info/METADATA
pickaa-1.0.0.dist-info/WHEEL
pickaa-1.0.0.dist-info/entry_points.txt
pickaa-1.0.0.dist-info/top_level.txt
pickaa-1.0.0.dist-info/RECORD
