Metadata-Version: 2.1
Name: pickaa
Version: 1.0.0
Summary: Random Argument Picker
Home-page: https://github.com/joshikeno/pickaa
Author: Josh Ike
Author-email: joshike.no@gmail.com
License: UNKNOWN
Platform: UNKNOWN
Requires-Dist: click
